django_reactions/__init__.py
django_reactions/apps.py
django_reactions/conf.py
django_reactions/enums.py
django_reactions/loaders.py
django_reactions/models.py
django_reactions/tests.py
django_reactions-0.0.1.dist-info/METADATA
django_reactions-0.0.1.dist-info/WHEEL
django_reactions-0.0.1.dist-info/top_level.txt
django_reactions-0.0.1.dist-info/RECORD
